cosyvoice/__init__.py
cosyvoice/bin/average_model.py
cosyvoice/bin/export_jit.py
cosyvoice/bin/export_onnx.py
cosyvoice/bin/inference_deprecated.py
cosyvoice/bin/train.py
cosyvoice/bin/upload_weights.py
cosyvoice/cli/__init__.py
cosyvoice/cli/cosyvoice.py
cosyvoice/cli/frontend.py
cosyvoice/cli/model.py
cosyvoice/dataset/__init__.py
cosyvoice/dataset/dataset.py
cosyvoice/dataset/processor.py
cosyvoice/flow/decoder.py
cosyvoice/flow/flow.py
cosyvoice/flow/flow_matching.py
cosyvoice/flow/length_regulator.py
cosyvoice/hifigan/discriminator.py
cosyvoice/hifigan/f0_predictor.py
cosyvoice/hifigan/generator.py
cosyvoice/hifigan/hifigan.py
cosyvoice/llm/llm.py
cosyvoice/tokenizer/tokenizer.py
cosyvoice/transformer/__init__.py
cosyvoice/transformer/activation.py
cosyvoice/transformer/attention.py
cosyvoice/transformer/convolution.py
cosyvoice/transformer/decoder.py
cosyvoice/transformer/decoder_layer.py
cosyvoice/transformer/embedding.py
cosyvoice/transformer/encoder.py
cosyvoice/transformer/encoder_layer.py
cosyvoice/transformer/label_smoothing_loss.py
cosyvoice/transformer/positionwise_feed_forward.py
cosyvoice/transformer/subsampling.py
cosyvoice/transformer/upsample_encoder.py
cosyvoice/utils/__init__.py
cosyvoice/utils/class_utils.py
cosyvoice/utils/common.py
cosyvoice/utils/executor.py
cosyvoice/utils/file_utils.py
cosyvoice/utils/frontend_utils.py
cosyvoice/utils/losses.py
cosyvoice/utils/mask.py
cosyvoice/utils/scheduler.py
cosyvoice/utils/train_utils.py
cosyvoice/vllm/cosyvoice2.py
cosyvoice2_fr/__init__.py
cosyvoice2_fr/cli.py
cosyvoice2_fr_infer-0.1.5.dist-info/licenses/LICENSE
matcha/__init__.py
matcha/app.py
matcha/cli.py
matcha/train.py
matcha/hifigan/__init__.py
matcha/hifigan/config.py
matcha/hifigan/denoiser.py
matcha/hifigan/env.py
matcha/hifigan/meldataset.py
matcha/hifigan/models.py
matcha/hifigan/xutils.py
matcha/models/__init__.py
matcha/models/baselightningmodule.py
matcha/models/matcha_tts.py
matcha/models/components/__init__.py
matcha/models/components/decoder.py
cosyvoice2_fr_infer-0.1.5.dist-info/METADATA
cosyvoice2_fr_infer-0.1.5.dist-info/WHEEL
cosyvoice2_fr_infer-0.1.5.dist-info/entry_points.txt
cosyvoice2_fr_infer-0.1.5.dist-info/top_level.txt
cosyvoice2_fr_infer-0.1.5.dist-info/RECORD
