Metadata-Version: 2.4
Name: cosyvoice2-fr-infer
Version: 0.1.5
Summary: Minimal CosyVoice2 French inference CLI (bundles runtime + Matcha)
Author-email: Tim Luka Horstmann <lukahorstmann@gmx.de>
License: Apache-2.0
Project-URL: homepage, https://huggingface.co/Luka512/CosyVoice2-0.5B-FR
Keywords: tts,text-to-speech,cosyvoice,french,voice-cloning
Classifier: Development Status :: 4 - Beta
Classifier: Intended Audience :: Developers
Classifier: Intended Audience :: Science/Research
Classifier: License :: OSI Approved :: Apache Software License
Classifier: Operating System :: OS Independent
Classifier: Programming Language :: Python :: 3
Classifier: Programming Language :: Python :: 3.9
Classifier: Programming Language :: Python :: 3.10
Classifier: Programming Language :: Python :: 3.11
Classifier: Topic :: Multimedia :: Sound/Audio :: Speech
Classifier: Topic :: Scientific/Engineering :: Artificial Intelligence
Requires-Python: >=3.9
License-File: LICENSE
Requires-Dist: torch>=2.3
Requires-Dist: torchaudio>=2.3
Requires-Dist: onnxruntime; platform_system != "Linux"
Requires-Dist: onnxruntime-gpu; platform_system == "Linux"
Requires-Dist: openai-whisper
Requires-Dist: hyperpyyaml>=1.2
Requires-Dist: huggingface_hub>=0.24
Requires-Dist: WeTextProcessing>=1.0.3
Requires-Dist: inflect>=7.0
Requires-Dist: numpy==1.26
Requires-Dist: tqdm>=4.66
Requires-Dist: soundfile>=0.12
Requires-Dist: transformers==4.40.1
Requires-Dist: diffusers>=0.29
Requires-Dist: modelscope>=1.20
Requires-Dist: omegaconf>=2.3
Requires-Dist: conformer>=0.3.2
Requires-Dist: hydra-core>=1.3
Requires-Dist: einops>=0.6
Requires-Dist: librosa>=0.10
Requires-Dist: scipy>=1.10
Requires-Dist: matplotlib>=3.6
Requires-Dist: rich>=13.0
Requires-Dist: lightning>=2.0
Requires-Dist: rootutils>=1.0
Requires-Dist: gdown>=4.7
Requires-Dist: wget>=3.2
Requires-Dist: phonemizer>=3.0
Requires-Dist: unidecode>=1.3
Requires-Dist: pyyaml>=6.0
Requires-Dist: deepspeed>=0.10
Requires-Dist: pyarrow>=10.0
Requires-Dist: pyworld>=0.3.0
Provides-Extra: piper
Requires-Dist: piper-phonemize>=1.0; extra == "piper"
Dynamic: license-file
